cpus/__init__.py
cpus/_modidx.py
cpus/core.py
cpus-0.0.3.dist-info/LICENSE
cpus-0.0.3.dist-info/METADATA
cpus-0.0.3.dist-info/WHEEL
cpus-0.0.3.dist-info/entry_points.txt
cpus-0.0.3.dist-info/top_level.txt
cpus-0.0.3.dist-info/RECORD
