Metadata-Version: 2.1
Name: cpus
Version: 0.0.3
Summary: cpus
Home-page: https://github.com/dsm-72/cpus
Author: dsm-72
Author-email: sumner.magruder@yale.edu
License: Apache Software License 2.0
Keywords: cpus is question bool type guard typeguard check cpus
Classifier: Development Status :: 4 - Beta
Classifier: Intended Audience :: Developers
Classifier: Natural Language :: English
Classifier: Programming Language :: Python :: 3.11
Classifier: License :: OSI Approved :: Apache Software License
Requires-Python: >=3.11
License-File: LICENSE
Requires-Dist: joblib
Provides-Extra: dev
Requires-Dist: joblib ; extra == 'dev'
